sl_experiment/__init__.py
sl_experiment/py.typed
sl_experiment/command_line_interfaces/__init__.py
sl_experiment/command_line_interfaces/entry_points.py
sl_experiment/command_line_interfaces/execute.py
sl_experiment/command_line_interfaces/get.py
sl_experiment/command_line_interfaces/manage.py
sl_experiment/command_line_interfaces/mcp_servers.py
sl_experiment/mesoscope_vr/__init__.py
sl_experiment/mesoscope_vr/binding_classes.py
sl_experiment/mesoscope_vr/data_acquisition.py
sl_experiment/mesoscope_vr/data_preprocessing.py
sl_experiment/mesoscope_vr/maintenance_ui.py
sl_experiment/mesoscope_vr/runtime_ui.py
sl_experiment/mesoscope_vr/tools.py
sl_experiment/mesoscope_vr/visualizers.py
sl_experiment/mesoscope_vr/zaber_bindings.py
sl_experiment/shared_components/__init__.py
sl_experiment/shared_components/google_sheet_tools.py
sl_experiment/shared_components/module_interfaces.py
sl_experiment/shared_components/shared_assets.py
sl_experiment-4.0.0.dist-info/METADATA
sl_experiment-4.0.0.dist-info/WHEEL
sl_experiment-4.0.0.dist-info/entry_points.txt
sl_experiment-4.0.0.dist-info/licenses/LICENSE
sl_experiment-4.0.0.dist-info/RECORD
