Metadata-Version: 2.4
Name: sl-experiment
Version: 4.0.0
Summary: Provides the assets for acquiring and preprocessing scientific data in the Sun (NeuroAI) lab.
Project-URL: Homepage, https://github.com/Sun-Lab-NBB/sl-experiment
Project-URL: Documentation, https://sl-experiment-api-docs.netlify.app/
Author: Ivan Kondratyev, Kushaan Gupta, Natalie Yeung, Katlynn Ryu, Jasmine Si
Maintainer-email: Ivan Kondratyev <ik278@cornell.edu>
License:                     GNU GENERAL PUBLIC LICENSE
License-File: LICENSE
Keywords: acquisition,ataraxis,data,experiment,interface,mesoscope,sunlab
Classifier: Development Status :: 5 - Production/Stable
Classifier: Intended Audience :: Science/Research
Classifier: License :: OSI Approved :: GNU General Public License v3 or later (GPLv3+)
Classifier: Operating System :: POSIX :: Linux
Classifier: Programming Language :: Python :: 3.14
Classifier: Topic :: Scientific/Engineering
Classifier: Typing :: Typed
Requires-Python: <3.15,>=3.14
Requires-Dist: appdirs==1.4.4
Requires-Dist: ataraxis-base-utilities==5.0.0
Requires-Dist: ataraxis-communication-interface==4.2.0
Requires-Dist: ataraxis-data-structures==5.0.0
Requires-Dist: ataraxis-time==5.0.0
Requires-Dist: ataraxis-transport-layer-pc==3.1.1
Requires-Dist: ataraxis-video-system==2.3.0
Requires-Dist: click==8.3.1
Requires-Dist: crc==7.1.0
Requires-Dist: google-api-python-client==2.188.0
Requires-Dist: httpx<1,>=0.27
Requires-Dist: imagecodecs==2026.1.14
Requires-Dist: importlib-metadata==8.7.1
Requires-Dist: intel-cmplr-lib-rt==2025.3.2; platform_system != 'Darwin'
Requires-Dist: matplotlib==3.10.8
Requires-Dist: mcp<2,>=1
Requires-Dist: natsort-rs==0.1.17
Requires-Dist: numba==0.63.1
Requires-Dist: numpy==2.3.5
Requires-Dist: pyqt6==6.10.2
Requires-Dist: scipy==1.17.0
Requires-Dist: sl-shared-assets==7.0.0
Requires-Dist: tabulate2==1.10.2
Requires-Dist: tifffile==2026.1.14
Requires-Dist: tqdm==4.67.1
Requires-Dist: zaber-motion==8.0.3
Provides-Extra: dev
Requires-Dist: ataraxis-automation<8,>=7; extra == 'dev'
Requires-Dist: google-api-python-client-stubs<2,>=1; extra == 'dev'
Requires-Dist: scipy-stubs<2,>=1; extra == 'dev'
Requires-Dist: tox-uv<2,>=1; extra == 'dev'
Requires-Dist: tox<5,>=4; extra == 'dev'
Requires-Dist: types-appdirs<2,>=1; extra == 'dev'
Requires-Dist: types-tabulate<1,>=0; extra == 'dev'
Requires-Dist: types-tqdm<5,>=4; extra == 'dev'
Requires-Dist: uv<1,>=0; extra == 'dev'
